README.txt
setup.py
src/pydir/__init__.py
src/pydir.egg-info/PKG-INFO
src/pydir.egg-info/SOURCES.txt
src/pydir.egg-info/dependency_links.txt
src/pydir.egg-info/entry_points.txt
src/pydir.egg-info/top_level.txt