Metadata-Version: 1.0
Name: pydir
Version: 0.2.1
Summary: Pydir is mkdir for Python modules
Home-page: https://github.com/nathforge/pydir
Author: Nathan Reynolds
Author-email: email@nreynolds.co.uk
License: UNKNOWN
Platform: UNKNOWN
